MANIFEST.in
README.md
README.rst
__init__.py
action.py
conf.py
decorators.py
eventbus.py
executors.py
finder.py
msg.py
package.py
registry.py
requirements.txt
setup.py
subscriber.py
tests.py
pyeventbus2.egg-info/PKG-INFO
pyeventbus2.egg-info/SOURCES.txt
pyeventbus2.egg-info/dependency_links.txt
pyeventbus2.egg-info/top_level.txt
pyeventbus2.egg-info/zip-safe