Metadata-Version: 2.1
Name: pyeventbus2
Version: 1.0.0
Summary: Lightweight event bus support sync and async, inspired by google guava event bus
Home-page: https://github.com/jxs1211/pyeventbus
Author: shenxianjie
Author-email: 327411586@qq.com
License: MIT
Keywords: eventbus
Platform: all
Classifier: Programming Language :: Python :: 3.7
Classifier: License :: OSI Approved :: MIT License
Classifier: Operating System :: OS Independent
